sci_soft_models/__init__.py
sci_soft_models/py.typed
sci_soft_models/types.py
sci_soft_models/dev_author_em/__init__.py
sci_soft_models/dev_author_em/constants.py
sci_soft_models/dev_author_em/exp.py
sci_soft_models/dev_author_em/main.py
sci_soft_models/dev_author_em/training.py
sci_soft_models/dev_author_em/data/__init__.py
sci_soft_models/dev_author_em/data/files/annotated-dev-author-em-resolved.csv
sci_soft_models/dev_author_em/data/files/extended-paper-details.parquet
sci_soft_models/dev_author_em/data/files/joss-short-paper-details.parquet
sci_soft_models/dev_author_em/data/files/repo-contributors.parquet
sci_soft_models/dev_author_em/data/files/softwarex-short-paper-details.parquet
sci_soft_models/dev_author_em/data/files/experiments/exp-training-results.csv
sci_soft_models/dev_author_em/data/files/final-model-training-data/dev-author-em-confusion-matrix.png
sci_soft_models/dev_author_em/data/files/final-model-training-data/dev-author-em-misclassifications.csv
sci_soft_models/dev_author_em/data/files/final-model-training-data/results.json
sci_soft_models/dev_author_em/data/files/final-model-training-data/split-counts.parquet
sci_soft_models/dev_author_em/data/files/final-model-training-data/test-set.parquet
sci_soft_models/dev_author_em/data/files/final-model-training-data/train-set.parquet
sci_soft_models/tests/test_dev_author_em.py
sci_soft_models-0.3.3.dist-info/LICENSE
sci_soft_models-0.3.3.dist-info/METADATA
sci_soft_models-0.3.3.dist-info/WHEEL
sci_soft_models-0.3.3.dist-info/top_level.txt
sci_soft_models-0.3.3.dist-info/RECORD
