Metadata-Version: 2.1
Name: sci-soft-models
Version: 0.3.3
Summary: Computational Models for Understanding Scientific Software
Author-email: Eva Maxfield Brown <evamaxfieldbrown@gmail.com>
License: MIT License
Project-URL: Homepage, https://github.com/evamaxfield/sci-soft-models
Project-URL: Bug Tracker, https://github.com/evamaxfield/sci-soft-models/issues
Project-URL: Documentation, https://evamaxfield.github.io/sci-soft-models
Project-URL: User Support, https://github.com/evamaxfield/sci-soft-models/issues
Classifier: Development Status :: 4 - Beta
Classifier: Natural Language :: English
Classifier: Programming Language :: Python :: 3.10
Classifier: Programming Language :: Python :: 3.11
Classifier: Programming Language :: Python :: 3.12
Requires-Python: >=3.10
License-File: LICENSE
Requires-Dist: dataclasses-json<0.7,>=0.6
Requires-Dist: requests<3,>=2
Requires-Dist: torch<3,>=2
Requires-Dist: transformers<5,>=4
Provides-Extra: lint
Requires-Dist: pre-commit>=2.20.0; extra == "lint"
Provides-Extra: dev
Requires-Dist: ipython; extra == "dev"
Requires-Dist: jupyterlab; extra == "dev"
Provides-Extra: test
Requires-Dist: pytest<9,>=8; extra == "test"
Provides-Extra: training
Requires-Dist: autotrain-advanced<0.9,>=0.8; extra == "training"
Requires-Dist: datasets<3,>=2; extra == "training"
Requires-Dist: python-dotenv==1.0.1; extra == "training"
Requires-Dist: pandas<3,>=1; extra == "training"
Requires-Dist: pyarrow>=12; extra == "training"
Requires-Dist: tabulate<0.10,>=0.9; extra == "training"
Requires-Dist: tqdm<5,>=4; extra == "training"
